pydracs/__init__.py
pydracs/cli.py
pydracs/pydracs.py
pydracs/devices/GPIO.py
pydracs/devices/__init__.py
pydracs/devices/buttons.py
pydracs/network/__init__.py
pydracs/utils/__init__.py
pydracs/utils/checks.py
pydracs-0.1.1.dist-info/AUTHORS.rst
pydracs-0.1.1.dist-info/LICENSE
pydracs-0.1.1.dist-info/METADATA
pydracs-0.1.1.dist-info/WHEEL
pydracs-0.1.1.dist-info/entry_points.txt
pydracs-0.1.1.dist-info/top_level.txt
pydracs-0.1.1.dist-info/RECORD
