Metadata-Version: 2.1
Name: pydracs
Version: 0.1.1
Summary: Distributed control and communications system mainly targeted at single board computers such as the raspberry pi.
Home-page: https://github.com/cfekete93/pydracs
Author: Christopher S. Fekete
Author-email: cfekete93@hotmail.com
License: MIT license
Keywords: pydracs
Platform: UNKNOWN
Classifier: Development Status :: 2 - Pre-Alpha
Classifier: Intended Audience :: Developers
Classifier: License :: OSI Approved :: MIT License
Classifier: Natural Language :: English
Classifier: Programming Language :: Python :: 2
Classifier: Programming Language :: Python :: 2.7
Classifier: Programming Language :: Python :: 3
Classifier: Programming Language :: Python :: 3.4
Classifier: Programming Language :: Python :: 3.5
Classifier: Programming Language :: Python :: 3.6
Classifier: Programming Language :: Python :: 3.7
Requires-Dist: Click (>=6.0)
Provides-Extra: gpio
Requires-Dist: RPi.GPIO; extra == 'gpio'
